{
  "status": 200,
  "message": "Success",
  "data": {
    "content": [
      {
        "id": 2,
        "barcode": "8991234567890",
        "name": "Kopi Arabika Premium 200g",
        "description": "Kopi arabika pilihan dengan aroma khas",
        "costPrice": 25000,
        "salePrice": 35000,
        "stock": 100,
        "picturePath": "",
        "isActive": true,
        "categoryId": null,
        "uomId": null
      },
      {
        "id": 3,
        "barcode": "8991234567891",
        "name": "Teh Melati 100g",
        "description": "Teh melati dengan aroma yang menenangkan",
        "costPrice": 15000,
        "salePrice": 25000,
        "stock": 150,
        "picturePath": "",
        "isActive": true,
        "categoryId": null,
        "uomId": null
      },
      {
        "id": 4,
        "barcode": "8991234567892",
        "name": "Gula Pasir 1kg",
        "description": "Gula pasir putih bersih",
        "costPrice": 12000,
        "salePrice": 18000,
        "stock": 200,
        "picturePath": "",
        "isActive": true,
        "categoryId": null,
        "uomId": null
      },
      {
        "id": 5,
        "barcode": "8991234567893",
        "name": "Susu Kental Manis",
        "description": "Susu kental manis untuk berbagai keperluan",
        "costPrice": 8000,
        "salePrice": 12000,
        "stock": 120,
        "picturePath": "",
        "isActive": true,
        "categoryId": null,
        "uomId": null
      },
      {
        "id": 6,
        "barcode": "8991234567894",
        "name": "Sirup Cocopandan",
        "description": "Sirup rasa cocopandan yang menyegarkan",
        "costPrice": 18000,
        "salePrice": 28000,
        "stock": 80,
        "picturePath": "",
        "isActive": true,
        "categoryId": null,
        "uomId": null
      },
      {
        "id": 7,
        "barcode": "8991234567895",
        "name": "Mie Instan Goreng",
        "description": "Mie instan goreng rasa original",
        "costPrice": 2500,
        "salePrice": 3500,
        "stock": 300,
        "picturePath": "",
        "isActive": true,
        "categoryId": null,
        "uomId": null
      },
      {
        "id": 8,
        "barcode": "8991234567896",
        "name": "Minyak Goreng 1L",
        "description": "Minyak goreng kelapa sawit",
        "costPrice": 15000,
        "salePrice": 20000,
        "stock": 100,
        "picturePath": "",
        "isActive": true,
        "categoryId": null,
        "uomId": null
      },
      {
        "id": 9,
        "barcode": "8991234567897",
        "name": "Tepung Terigu 1kg",
        "description": "Tepung terigu serbaguna",
        "costPrice": 10000,
        "salePrice": 15000,
        "stock": 150,
        "picturePath": "",
        "isActive": true,
        "categoryId": null,
        "uomId": null
      },
      {
        "id": 10,
        "barcode": "8991234567898",
        "name": "Kecap Manis 600ml",
        "description": "Kecap manis berkualitas",
        "costPrice": 12000,
        "salePrice": 18000,
        "stock": 120,
        "picturePath": "",
        "isActive": true,
        "categoryId": null,
        "uomId": null
      },
      {
        "id": 11,
        "barcode": "8991234567899",
        "name": "Sambal Botol",
        "description": "Sambal pedas nikmat",
        "costPrice": 8000,
        "salePrice": 12000,
        "stock": 80,
        "picturePath": "",
        "isActive": true,
        "categoryId": null,
        "uomId": null
      },
      {
        "id": 12,
        "barcode": "8991234567900",
        "name": "Beras 5kg",
        "description": "Beras pulen dan wangi",
        "costPrice": 50000,
        "salePrice": 60000,
        "stock": 50,
        "picturePath": "",
        "isActive": true,
        "categoryId": null,
        "uomId": null
      },
      {
        "id": 13,
        "barcode": "8991234567901",
        "name": "Telur Ayam 1kg",
        "description": "Telur ayam segar",
        "costPrice": 20000,
        "salePrice": 25000,
        "stock": 100,
        "picturePath": "",
        "isActive": true,
        "categoryId": null,
        "uomId": null
      },
      {
        "id": 14,
        "barcode": "8991234567902",
        "name": "Bawang Merah 250g",
        "description": "Bawang merah segar",
        "costPrice": 8000,
        "salePrice": 12000,
        "stock": 150,
        "picturePath": "",
        "isActive": true,
        "categoryId": null,
        "uomId": null
      },
      {
        "id": 15,
        "barcode": "8991234567903",
        "name": "Bawang Putih 250g",
        "description": "Bawang putih segar",
        "costPrice": 8000,
        "salePrice": 12000,
        "stock": 150,
        "picturePath": "",
        "isActive": true,
        "categoryId": null,
        "uomId": null
      },
      {
        "id": 16,
        "barcode": "8991234567904",
        "name": "Deterjen Bubuk 1kg",
        "description": "Deterjen bubuk untuk mencuci pakaian",
        "costPrice": 20000,
        "salePrice": 28000,
        "stock": 80,
        "picturePath": "",
        "isActive": true,
        "categoryId": null,
        "uomId": null
      },
      {
        "id": 17,
        "barcode": "8991234567905",
        "name": "Sabun Mandi",
        "description": "Sabun mandi dengan aroma segar",
        "costPrice": 3000,
        "salePrice": 5000,
        "stock": 200,
        "picturePath": "",
        "isActive": true,
        "categoryId": null,
        "uomId": null
      },
      {
        "id": 18,
        "barcode": "8991234567906",
        "name": "Pasta Gigi",
        "description": "Pasta gigi untuk gigi sehat dan kuat",
        "costPrice": 5000,
        "salePrice": 8000,
        "stock": 150,
        "picturePath": "",
        "isActive": true,
        "categoryId": null,
        "uomId": null
      },
      {
        "id": 19,
        "barcode": "8991234567907",
        "name": "Shampo",
        "description": "Shampo untuk rambut sehat dan berkilau",
        "costPrice": 10000,
        "salePrice": 15000,
        "stock": 100,
        "picturePath": "",
        "isActive": true,
        "categoryId": null,
        "uomId": null
      },
      {
        "id": 20,
        "barcode": "8991234567908",
        "name": "Korek Api",
        "description": "Korek api gas",
        "costPrice": 2000,
        "salePrice": 3000,
        "stock": 200,
        "picturePath": "",
        "isActive": true,
        "categoryId": null,
        "uomId": null
      },
      {
        "id": 21,
        "barcode": "8991234567909",
        "name": "Baterai AA",
        "description": "Baterai AA isi 2",
        "costPrice": 5000,
        "salePrice": 8000,
        "stock": 150,
        "picturePath": "",
        "isActive": true,
        "categoryId": null,
        "uomId": null
      }
    ],
    "page": 0,
    "size": 20,
    "totalElements": 20,
    "totalPages": 1,
    "first": true,
    "last": true,
    "empty": false,
    "sort": "id",
    "direction": "desc"
  },
  "errors": null,
  "timestamp": "2025-11-07T00:07:36.765099"
}